wikitextprocessor/__init__.py
wikitextprocessor/common.py
wikitextprocessor/core.py
wikitextprocessor/dumpparser.py
wikitextprocessor/languages.py
wikitextprocessor/luaexec.py
wikitextprocessor/node_expand.py
wikitextprocessor/parser.py
wikitextprocessor/parserfns.py
wikitextprocessor/wikihtml.py
wikitextprocessor/lua/_sandbox_phase1.lua
wikitextprocessor/lua/_sandbox_phase2.lua
wikitextprocessor/lua/mw.lua
wikitextprocessor/lua/mw_hash.lua
wikitextprocessor/lua/mw_html.lua
wikitextprocessor/lua/mw_language.lua
wikitextprocessor/lua/mw_site.lua
wikitextprocessor/lua/mw_text.lua
wikitextprocessor/lua/mw_title.lua
wikitextprocessor/lua/mw_uri.lua
wikitextprocessor/lua/mw_wikibase.lua
wikitextprocessor/lua/mediawiki-extensions-Scribunto/COPYING
wikitextprocessor/lua/mediawiki-extensions-Scribunto/includes/engines/LuaCommon/lualib/bit32.lua
wikitextprocessor/lua/mediawiki-extensions-Scribunto/includes/engines/LuaCommon/lualib/libraryUtil.lua
wikitextprocessor/lua/mediawiki-extensions-Scribunto/includes/engines/LuaCommon/lualib/mw.hash.lua
wikitextprocessor/lua/mediawiki-extensions-Scribunto/includes/engines/LuaCommon/lualib/mw.html.lua
wikitextprocessor/lua/mediawiki-extensions-Scribunto/includes/engines/LuaCommon/lualib/mw.language.lua
wikitextprocessor/lua/mediawiki-extensions-Scribunto/includes/engines/LuaCommon/lualib/mw.lua
wikitextprocessor/lua/mediawiki-extensions-Scribunto/includes/engines/LuaCommon/lualib/mw.message.lua
wikitextprocessor/lua/mediawiki-extensions-Scribunto/includes/engines/LuaCommon/lualib/mw.site.lua
wikitextprocessor/lua/mediawiki-extensions-Scribunto/includes/engines/LuaCommon/lualib/mw.text.lua
wikitextprocessor/lua/mediawiki-extensions-Scribunto/includes/engines/LuaCommon/lualib/mw.title.lua
wikitextprocessor/lua/mediawiki-extensions-Scribunto/includes/engines/LuaCommon/lualib/mw.uri.lua
wikitextprocessor/lua/mediawiki-extensions-Scribunto/includes/engines/LuaCommon/lualib/mw.ustring.lua
wikitextprocessor-0.4.96.dist-info/LICENSE
wikitextprocessor-0.4.96.dist-info/METADATA
wikitextprocessor-0.4.96.dist-info/WHEEL
wikitextprocessor-0.4.96.dist-info/top_level.txt
wikitextprocessor-0.4.96.dist-info/RECORD
