Metadata-Version: 2.1
Name: wikitextprocessor
Version: 0.4.96
Summary: Parser and expander for Wikipedia, Wiktionary etc. dump files, with Lua execution support
Home-page: https://github.com/tatuylonen/wikitextprocessor
Author: Tatu Ylonen
Author-email: ylo@clausal.com
License: MIT (some included files have other free licences)
Download-URL: https://github.com/tatuylonen/wikitextprocessor
Keywords: dictionary,wiktionary,wikipedia,data extraction,wikitext,scribunto,lua
Platform: UNKNOWN
Classifier: Development Status :: 3 - Alpha
Classifier: Intended Audience :: Developers
Classifier: Intended Audience :: Science/Research
Classifier: License :: OSI Approved :: MIT License
Classifier: Natural Language :: English
Classifier: Operating System :: POSIX :: Linux
Classifier: Programming Language :: Python
Classifier: Programming Language :: Python :: 3 :: Only
Classifier: Topic :: Text Processing
Classifier: Topic :: Text Processing :: Linguistic
License-File: LICENSE
